{
  "$defs": {
    "File": {
      "$id": "/schemas/File",
      "oneOf": [
        {
          "description": "A class representing a file in the inference.sh ecosystem.",
          "properties": {
            "uri": {
              "anyOf": [
                {
                  "type": "string"
                },
                {
                  "type": "null"
                }
              ],
              "default": null,
              "title": "Uri"
            },
            "path": {
              "anyOf": [
                {
                  "type": "string"
                },
                {
                  "type": "null"
                }
              ],
              "default": null,
              "title": "Path"
            },
            "content_type": {
              "anyOf": [
                {
                  "type": "string"
                },
                {
                  "type": "null"
                }
              ],
              "default": null,
              "title": "Content Type"
            },
            "size": {
              "anyOf": [
                {
                  "type": "integer"
                },
                {
                  "type": "null"
                }
              ],
              "default": null,
              "title": "Size"
            },
            "filename": {
              "anyOf": [
                {
                  "type": "string"
                },
                {
                  "type": "null"
                }
              ],
              "default": null,
              "title": "Filename"
            }
          },
          "title": "File",
          "type": "object"
        },
        {
          "type": "string"
        }
      ]
    }
  },
  "description": "Input schema for Dia TTS.",
  "properties": {
    "text": {
      "description": "The text to convert to speech. Use [S1], [S2] for multi-speaker dialogue and (laughs), (sighs) for nonverbals.",
      "title": "Text",
      "type": "string"
    },
    "ref_audio": {
      "anyOf": [
        {
          "$ref": "#/$defs/File"
        },
        {
          "type": "null"
        }
      ],
      "default": null,
      "description": "Reference audio file for voice cloning. If provided, ref_text is also required."
    },
    "ref_text": {
      "anyOf": [
        {
          "type": "string"
        },
        {
          "type": "null"
        }
      ],
      "default": null,
      "description": "Transcript of the reference audio. Required when using voice cloning.",
      "title": "Ref Text"
    }
  },
  "required": [
    "text"
  ],
  "title": "AppInput",
  "type": "object"
}